CommercialScraper/__init__.py
CommercialScraper/data_processing.py
CommercialScraper/pipeline.py
CommercialScraper-1.0.0.dist-info/LICENSE
CommercialScraper-1.0.0.dist-info/METADATA
CommercialScraper-1.0.0.dist-info/WHEEL
CommercialScraper-1.0.0.dist-info/top_level.txt
CommercialScraper-1.0.0.dist-info/RECORD
