Metadata-Version: 2.1
Name: CommercialScraper
Version: 1.0.0
Summary: A dynamic and scalable data pipeline from Airbnbs commercial site to your local system / cloud storage.
Home-page: https://github.com/4ldrich/CommercialScraper
Author: Omar 4ldrich Tahmas
Author-email: o.ismail@aol.co.uk
License: UNKNOWN
Platform: UNKNOWN
Classifier: Programming Language :: Python :: 3
Classifier: License :: OSI Approved :: MIT License
Classifier: Operating System :: OS Independent
Requires-Python: >=3.6
Requires-Dist: boto3 (>=1.20.10)
Requires-Dist: botocore (>=1.22.8)
Requires-Dist: greenlet (>=1.1.2)
Requires-Dist: jmespath (>=0.10.0)
Requires-Dist: numpy (>=1.21.4)
Requires-Dist: pandas (>=1.3.4)
Requires-Dist: psycopg2 (>=2.9.2)
Requires-Dist: pytz (>=2021.3)
Requires-Dist: s3transfer (>=0.5.0)
Requires-Dist: selenium (>=3.141.0)
Requires-Dist: six (>=1.16.0)
Requires-Dist: SQLAlchemy (>=1.4.27)
Requires-Dist: urllib3 (>=1.26.7)
